shadePy/__init__.py
shadePy/static.py
shadePy-1.0.0.dist-info/LICENSE
shadePy-1.0.0.dist-info/METADATA
shadePy-1.0.0.dist-info/WHEEL
shadePy-1.0.0.dist-info/top_level.txt
shadePy-1.0.0.dist-info/RECORD
