Metadata-Version: 2.1
Name: shadePy
Version: 1.0.0
Summary: ShadePy is a robust Python library that offers an easy and user-friendly method for managing colors in the terminal. By 0x414854
Author-email: 0x414854 <autor@exemple.me>
License: MIT License
Project-URL: Documentation, https://github.com/0x414854/shadePy
Project-URL: Repository, https://github.com/0x414854/shadePy
Keywords: Color,Terminal,console,text styling,colored text,background color,Python
Classifier: Programming Language :: Python :: 3
Classifier: License :: OSI Approved :: MIT License
Classifier: Operating System :: OS Independent
Requires-Python: >=3.11
License-File: LICENSE
